SERGIO/__init__.py
SERGIO/_sergio.py
SERGIO/GRN/__init__.py
SERGIO/GRN/_components.py
SERGIO/GRN/_create.py
SERGIO/GRN/_grn.py
SERGIO/GRN/_utils.py
SERGIO/GRN/ref/EcoliNet.v1.txt
SERGIO/GRN/ref/__init__.py
SERGIO/GRN/ref/human.node
SERGIO/GRN/ref/human.source
SERGIO/MR/__init__.py
SERGIO/MR/_profile.py
SERGIO/Noise/__init__.py
SERGIO/Noise/_noise.py
sergio_scSim-1.9.3.dist-info/LICENSE
sergio_scSim-1.9.3.dist-info/METADATA
sergio_scSim-1.9.3.dist-info/WHEEL
sergio_scSim-1.9.3.dist-info/top_level.txt
sergio_scSim-1.9.3.dist-info/RECORD
