Metadata-Version: 2.1
Name: sergio-scSim
Version: 1.9.3
Summary: SERGIO is a simulator for single-cell expression data guided by gene regulatory networks.
Home-page: https://github.com/PayamDiba/SERGIO
Author: Payam Dibaeinia
Author-email: dibaein2@illinois.edu
License: GNU GENERAL PUBLIC LICENSE
Platform: UNKNOWN
Classifier: Programming Language :: Python :: 3
Requires-Python: >3.5.2
License-File: LICENSE
Requires-Dist: numpy
Requires-Dist: pandas
Requires-Dist: absl-py
Requires-Dist: networkx
Requires-Dist: cma
Requires-Dist: matplotlib
Requires-Dist: scikit-learn
